chater/__init__.py
chater/api/__init__.py
chater/api/auth.py
chater/api/billing.py
chater/api/chabot.py
chater/api/models.py
chater/api/stream_completion.py
chater/api/utils.py
chater/api/abstract/__init__.py
chater/api/abstract/client.py
chater/api/abstract/typings.py
chater-1.0.8.dist-info/LICENSE
chater-1.0.8.dist-info/METADATA
chater-1.0.8.dist-info/WHEEL
chater-1.0.8.dist-info/top_level.txt
chater-1.0.8.dist-info/RECORD
