Metadata-Version: 2.1
Name: chater
Version: 1.0.8
Summary: Using ChatGPT in Python
Author: Sricor
Author-email: josricor@outlook.com
License: MIT
License-File: LICENSE
Requires-Dist: requests
Requires-Dist: pydantic
